{
    "taskDefinitionArn": "arn:aws:ecs:eu-north-1:337909773247:task-definition/node-td-3:1",
    "containerDefinitions": [
        {
            "name": "node-api",
            "image": "337909773247.dkr.ecr.eu-north-1.amazonaws.com/node-api:latest",
            "cpu": 0,
            "portMappings": [
                {
                    "name": "node-api-5000-tcp",
                    "containerPort": 5000,
                    "hostPort": 5000,
                    "protocol": "tcp",
                    "appProtocol": "http"
                }
            ],
            "essential": true,
            "environment": [
                {
                    "name": "MONGO_URI",
                    "value": "mongodb+srv://gorgino2020:WvjWHcGp6M5CVMdx@cluster0.v8cx4.mongodb.net/messages?retryWrites=true"
                }
            ],
            "environmentFiles": [],
            "mountPoints": [],
            "volumesFrom": [],
            "ulimits": [],
            "logConfiguration": {
                "logDriver": "awslogs",
                "options": {
                    "awslogs-group": "/ecs/node-td-3",
                    "mode": "non-blocking",
                    "awslogs-create-group": "true",
                    "max-buffer-size": "25m",
                    "awslogs-region": "eu-north-1",
                    "awslogs-stream-prefix": "ecs"
                },
                "secretOptions": []
            },
            "systemControls": []
        }
    ],
    "family": "node-td-3",
    "taskRoleArn": "arn:aws:iam::337909773247:role/ecsTaskExcutionRole",
    "executionRoleArn": "arn:aws:iam::337909773247:role/ecsTaskExcutionRole",
    "networkMode": "awsvpc",
    "revision": 1,
    "volumes": [],
    "status": "ACTIVE",
    "requiresAttributes": [
        {
            "name": "com.amazonaws.ecs.capability.logging-driver.awslogs"
        },
        {
            "name": "ecs.capability.execution-role-awslogs"
        },
        {
            "name": "com.amazonaws.ecs.capability.ecr-auth"
        },
        {
            "name": "com.amazonaws.ecs.capability.docker-remote-api.1.19"
        },
        {
            "name": "com.amazonaws.ecs.capability.docker-remote-api.1.28"
        },
        {
            "name": "com.amazonaws.ecs.capability.task-iam-role"
        },
        {
            "name": "ecs.capability.execution-role-ecr-pull"
        },
        {
            "name": "com.amazonaws.ecs.capability.docker-remote-api.1.18"
        },
        {
            "name": "ecs.capability.task-eni"
        },
        {
            "name": "com.amazonaws.ecs.capability.docker-remote-api.1.29"
        }
    ],
    "placementConstraints": [],
    "compatibilities": [
        "EC2",
        "FARGATE"
    ],
    "requiresCompatibilities": [
        "FARGATE"
    ],
    "cpu": "512",
    "memory": "1024",
    "runtimePlatform": {
        "cpuArchitecture": "X86_64",
        "operatingSystemFamily": "LINUX"
    },
    "registeredAt": "2024-08-18T14:50:11.994Z",
    "registeredBy": "arn:aws:iam::337909773247:root",
    "tags": []
}